diematic_server/__init__.py
diematic_server/boiler.py
diematic_server/diematicd.py
diematic_server/filelck.py
diematic_server/webserver.py
diematic_server-3.1.dist-info/LICENSE.txt
diematic_server-3.1.dist-info/METADATA
diematic_server-3.1.dist-info/WHEEL
diematic_server-3.1.dist-info/top_level.txt
diematic_server-3.1.dist-info/RECORD
