Metadata-Version: 2.1
Name: diematic_server
Version: 3.1
Summary: Unix daemon and supporting models for publishing data from Diematic DeDietrich boiler
Home-page: https://github.com/IgnacioHR/diematic_server
Download-URL: https://github.com/IgnacioHR/diematic_server/archive/refs/tags/v3.1.tar.gz
Author: Ignacio Hernández-Ros
Author-email: ignacio@hernandez-ros.com
License: MIT
Keywords: python,home-automation,iot,influxdb,restful,modbus,de-dietrich,diematic,mqtt
Classifier: Development Status :: 5 - Production/Stable
Classifier: Environment :: No Input/Output (Daemon)
Classifier: Intended Audience :: Developers
Classifier: License :: OSI Approved :: MIT License
Classifier: Operating System :: Unix
Classifier: Programming Language :: Python :: 3.11
Classifier: Topic :: Home Automation
License-File: LICENSE.txt
Requires-Dist: daemon==1.2
Requires-Dist: influxdb==5.2.3
Requires-Dist: pymodbus==2.2.0
Requires-Dist: python-daemon==2.3.0
Requires-Dist: PyYAML==6.0.2
Requires-Dist: aiohttp==3.11.2
Requires-Dist: paho-mqtt==2.1.0
